coba/__init__.py
coba/projec.py
cobapy-0.1.dist-info/METADATA
cobapy-0.1.dist-info/WHEEL
cobapy-0.1.dist-info/top_level.txt
cobapy-0.1.dist-info/RECORD
