Metadata-Version: 2.1
Name: cobapy
Version: 0.1
Summary: Projek singkat upload pypi
Home-page: https://link.ke/proyekmu
Author: Nur ridwan
Author-email: nurridwan270305@gmail.com
Classifier: Programming Language :: Python :: 3
Classifier: License :: OSI Approved :: MIT License
Classifier: Operating System :: OS Independent
Requires-Python: >=3.6
Requires-Dist: nama-dependensi1
Requires-Dist: nama-dependensi2
